llama_index/tools/aws_bedrock_agentcore/__init__.py
llama_index/tools/aws_bedrock_agentcore/browser/__init__.py
llama_index/tools/aws_bedrock_agentcore/browser/base.py
llama_index/tools/aws_bedrock_agentcore/browser/browser_session_manager.py
llama_index/tools/aws_bedrock_agentcore/browser/utils.py
llama_index/tools/aws_bedrock_agentcore/code_interpreter/__init__.py
llama_index/tools/aws_bedrock_agentcore/code_interpreter/base.py
llama_index_tools_aws_bedrock_agentcore-0.1.2.dist-info/METADATA
llama_index_tools_aws_bedrock_agentcore-0.1.2.dist-info/WHEEL
llama_index_tools_aws_bedrock_agentcore-0.1.2.dist-info/licenses/LICENSE
llama_index_tools_aws_bedrock_agentcore-0.1.2.dist-info/RECORD
