Metadata-Version: 2.4
Name: llama-index-tools-aws-bedrock-agentcore
Version: 0.1.2
Summary: llama-index tools AWS Bedrock AgentCore integration
Author-email: Your Name <you@example.com>
License-Expression: MIT
License-File: LICENSE
Keywords: agentcore,aws,bedrock
Requires-Python: <4.0,>=3.10
Requires-Dist: bedrock-agentcore>=0.1.0
Requires-Dist: boto3>=1.39.7
Requires-Dist: llama-index-core<0.15,>=0.12.0
Requires-Dist: playwright>=1.54.0
